div-testbench/clock-div.v
//Clock divider
module clock_divider #(

    //Parameters
    parameter  COUNT_WIDTH = 24,
    parameter[COUNT_WIDTH:0] MAX_COUNT = 6000000-1

)(

    //Inputs
    input clk,
    input rst,

    //Outputs
    output reg out

);


    //Internal Signals
    reg div_clk;
    reg[COUNT_WIDTH:0] count;

    //Clock divider
    always @ (posedge clk or posedge rst) begin
        if (rst==1'b1) begin
            count <= 0;
            out <= 0;
        end else if (count == MAX_COUNT) begin
            count <= 0;
            out <= ~out;
        end else begin 
            count <= count +1;
        end
    end
endmodule

div-testbench/clk-div_tb.v
//Define timescale for simulation : <time_unit>/<time_precision>
`timescale 1 ns /10 ps

//Define the testbench
module clock_divider_tb();

    //Internal signals
    wire out;

    //Storage elements (set initial values to 0)
    reg clk = 0;
    reg rst=0;

    //Simulation time: 10000*1ns=10 us
    localparam DURATION = 10000;

    //Generate clock signal:1 / (82*41.67)*1 ns) = 11,999,040.08 Mhz
    always begin

        //Delay for 41.67 time units
        //10 ps precision menans that 41.667 is rounded to 41.67 ns
        #41.667

        //Toggle clock line
        clk = ~clk;

    end

    //Instantiate the unit under test (UUT)
    clock_divider #(.COUNT_WIDTH(4), .MAX_COUNT(6)) uut(
        .clk(clk),
        .rst(rst),
        .out(out)
    );

    //Pulse reset line high at the beginning
    initial begin
        #10
        rst = 1'b1;
        #1
        rst = 1'b0;
    end

    //Run simulation (output to .vcd file)
    initial begin
        //Create simulatio n output file
        $dumpfile("clk-div_tb.vcd");
        $dumpvars(0, clock_divider_tb);

        //Wait for given amount of time for simulation to complete
        #(DURATION)

        //Notify and end simulation
        $display("Finished");
        $finish;
    end
    
endmodule

div-testbench/clk-div_tb.vcd
$date
	Mon Sep  7 14:18:12 2026
$end
$version
	Icarus Verilog
$end
$timescale
	10ps
$end
$scope module clock_divider_tb $end
$var wire 1 ! out $end
$var parameter 32 " DURATION $end
$var reg 1 # clk $end
$var reg 1 $ rst $end
$scope module uut $end
$var wire 1 # clk $end
$var wire 1 $ rst $end
$var parameter 32 % COUNT_WIDTH $end
$var parameter 5 & MAX_COUNT $end
$var reg 5 ' count [4:0] $end
$var reg 1 ! out $end
$upscope $end
$upscope $end
$enddefinitions $end
$comment Show the parameter values. $end
$dumpall
b110 &
b100 %
b10011100010000 "
$end
#0
$dumpvars
bx '
0$
0#
x!
$end
#1000
0!
b0 '
1$
#1100
0$
#4167
b1 '
1#
#8334
0#
#12501
b10 '
1#
#16668
0#
#20835
b11 '
1#
#25002
0#
#29169
b100 '
1#
#33336
0#
#37503
b101 '
1#
#41670
0#
#45837
b110 '
1#
#50004
0#
#54171
1!
b0 '
1#
#58338
0#
#62505
b1 '
1#
#66672
0#
#70839
b10 '
1#
#75006
0#
#79173
b11 '
1#
#83340
0#
#87507
b100 '
1#
#91674
0#
#95841
b101 '
1#
#100008
0#
#104175
b110 '
1#
#108342
0#
#112509
0!
b0 '
1#
#116676
0#
#120843
b1 '
1#
#125010
0#
#129177
b10 '
1#
#133344
0#
#137511
b11 '
1#
#141678
0#
#145845
b100 '
1#
#150012
0#
#154179
b101 '
1#
#158346
0#
#162513
b110 '
1#
#166680
0#
#170847
1!
b0 '
1#
#175014
0#
#179181
b1 '
1#
#183348
0#
#187515
b10 '
1#
#191682
0#
#195849
b11 '
1#
#200016
0#
#204183
b100 '
1#
#208350
0#
#212517
b101 '
1#
#216684
0#
#220851
b110 '
1#
#225018
0#
#229185
0!
b0 '
1#
#233352
0#
#237519
b1 '
1#
#241686
0#
#245853
b10 '
1#
#250020
0#
#254187
b11 '
1#
#258354
0#
#262521
b100 '
1#
#266688
0#
#270855
b101 '
1#
#275022
0#
#279189
b110 '
1#
#283356
0#
#287523
1!
b0 '
1#
#291690
0#
#295857
b1 '
1#
#300024
0#
#304191
b10 '
1#
#308358
0#
#312525
b11 '
1#
#316692
0#
#320859
b100 '
1#
#325026
0#
#329193
b101 '
1#
#333360
0#
#337527
b110 '
1#
#341694
0#
#345861
0!
b0 '
1#
#350028
0#
#354195
b1 '
1#
#358362
0#
#362529
b10 '
1#
#366696
0#
#370863
b11 '
1#
#375030
0#
#379197
b100 '
1#
#383364
0#
#387531
b101 '
1#
#391698
0#
#395865
b110 '
1#
#400032
0#
#404199
1!
b0 '
1#
#408366
0#
#412533
b1 '
1#
#416700
0#
#420867
b10 '
1#
#425034
0#
#429201
b11 '
1#
#433368
0#
#437535
b100 '
1#
#441702
0#
#445869
b101 '
1#
#450036
0#
#454203
b110 '
1#
#458370
0#
#462537
0!
b0 '
1#
#466704
0#
#470871
b1 '
1#
#475038
0#
#479205
b10 '
1#
#483372
0#
#487539
b11 '
1#
#491706
0#
#495873
b100 '
1#
#500040
0#
#504207
b101 '
1#
#508374
0#
#512541
b110 '
1#
#516708
0#
#520875
1!
b0 '
1#
#525042
0#
#529209
b1 '
1#
#533376
0#
#537543
b10 '
1#
#541710
0#
#545877
b11 '
1#
#550044
0#
#554211
b100 '
1#
#558378
0#
#562545
b101 '
1#
#566712
0#
#570879
b110 '
1#
#575046
0#
#579213
0!
b0 '
1#
#583380
0#
#587547
b1 '
1#
#591714
0#
#595881
b10 '
1#
#600048
0#
#604215
b11 '
1#
#608382
0#
#612549
b100 '
1#
#616716
0#
#620883
b101 '
1#
#625050
0#
#629217
b110 '
1#
#633384
0#
#637551
1!
b0 '
1#
#641718
0#
#645885
b1 '
1#
#650052
0#
#654219
b10 '
1#
#658386
0#
#662553
b11 '
1#
#666720
0#
#670887
b100 '
1#
#675054
0#
#679221
b101 '
1#
#683388
0#
#687555
b110 '
1#
#691722
0#
#695889
0!
b0 '
1#
#700056
0#
#704223
b1 '
1#
#708390
0#
#712557
b10 '
1#
#716724
0#
#720891
b11 '
1#
#725058
0#
#729225
b100 '
1#
#733392
0#
#737559
b101 '
1#
#741726
0#
#745893
b110 '
1#
#750060
0#
#754227
1!
b0 '
1#
#758394
0#
#762561
b1 '
1#
#766728
0#
#770895
b10 '
1#
#775062
0#
#779229
b11 '
1#
#783396
0#
#787563
b100 '
1#
#791730
0#
#795897
b101 '
1#
#800064
0#
#804231
b110 '
1#
#808398
0#
#812565
0!
b0 '
1#
#816732
0#
#820899
b1 '
1#
#825066
0#
#829233
b10 '
1#
#833400
0#
#837567
b11 '
1#
#841734
0#
#845901
b100 '
1#
#850068
0#
#854235
b101 '
1#
#858402
0#
#862569
b110 '
1#
#866736
0#
#870903
1!
b0 '
1#
#875070
0#
#879237
b1 '
1#
#883404
0#
#887571
b10 '
1#
#891738
0#
#895905
b11 '
1#
#900072
0#
#904239
b100 '
1#
#908406
0#
#912573
b101 '
1#
#916740
0#
#920907
b110 '
1#
#925074
0#
#929241
0!
b0 '
1#
#933408
0#
#937575
b1 '
1#
#941742
0#
#945909
b10 '
1#
#950076
0#
#954243
b11 '
1#
#958410
0#
#962577
b100 '
1#
#966744
0#
#970911
b101 '
1#
#975078
0#
#979245
b110 '
1#
#983412
0#
#987579
1!
b0 '
1#
#991746
0#
#995913
b1 '
1#
